[
  {
    "userNameId": 1,
    "postName": "Passenger Fall Away",
    "iframe": "https://www.youtube.com/embed/Q-ChG3jlgoc",
    "image": null,
    "video": null,
    "description": "Written by Mike Rosenberg\r\nPerformed by Mike Rosenberg & Stu Larsen\r\nRecorded by Chris Vallejo\r\nMixed by Chris Vallejo\r\nEdited & Graded by Nic Minns",
    "typeId": 2
  },
  {
    "userNameId": 1,
    "postName": "All out 80s",
    "iframe": "https://open.spotify.com/embed/playlist/37i9dQZF1DX4UtSsGT1Sbe",
    "image": null,
    "video": null,
    "description": "hola",
    "typeId": 2
  },
  {
    "userNameId": 1,
    "postName": "Esta no es mi guitarra",
    "iframe": null,
    "image": "com-1637453923429.jpg",
    "video": null,
    "description": "lorem ipsum dolor sit amet, consectetur adipiscing",
    "typeId": 3
  },
  {
    "userNameId": 1,
    "postName": "asdasdsa",
    "iframe": "https://www.youtube.com/embed/v4pi1LxuDHc",
    "image": null,
    "video": null,
    "description": "asdasgw",
    "typeId": 2
  },
  {
    "userNameId": 1,
    "postName": "Ed Sheeran",
    "iframe": "https://www.youtube.com/embed/FwoJkxtmCjw",
    "image": null,
    "video": null,
    "description": "Nueva cancion de ed sheeran",
    "typeId": 2
  }
]